cloudreactor_aws_setup_wizard/__init__.py
cloudreactor_aws_setup_wizard/__main__.py
cloudreactor_aws_setup_wizard/cloudreactor_api_client.py
cloudreactor_aws_setup_wizard/py.typed
cloudreactor_aws_setup_wizard/templates/vpc.yml.j2
cloudreactor_aws_setup_wizard/wizard.py
cloudreactor_aws_setup_wizard-1.4.0.dist-info/LICENSE
cloudreactor_aws_setup_wizard-1.4.0.dist-info/METADATA
cloudreactor_aws_setup_wizard-1.4.0.dist-info/WHEEL
cloudreactor_aws_setup_wizard-1.4.0.dist-info/entry_points.txt
cloudreactor_aws_setup_wizard-1.4.0.dist-info/RECORD
