Metadata-Version: 2.1
Name: cloudreactor-aws-setup-wizard
Version: 1.4.0
Summary: A command-line wizard to setup customer environments for running tasks managed by CloudReactor
Home-page: https://cloudreactor.io
License: BSD-2-Clause
Author: Jeff Tsay
Author-email: jeff@cloudreactor.io
Requires-Python: >=3.11,<4.0
Classifier: Development Status :: 4 - Beta
Classifier: Intended Audience :: Developers
Classifier: License :: OSI Approved :: BSD License
Classifier: Natural Language :: English
Classifier: Operating System :: OS Independent
Classifier: Programming Language :: Python :: 3
Classifier: Programming Language :: Python :: 3.11
Classifier: Topic :: Software Development :: Libraries
Requires-Dist: boto3 (>=1.26.137,<2.0.0)
Requires-Dist: jinja2 (>=3.1.2,<4.0.0)
Requires-Dist: jsonpickle (>=1.5.2,<2.0.0)
Requires-Dist: pyyaml (>=6.0,<7.0)
Requires-Dist: questionary (>=1.10.0,<2.0.0)
Requires-Dist: urllib3 (>=1.26.15,<2.0.0)
Project-URL: Bug Tracker, https://github.com/CloudReactor/cloudreactor-aws-setup-wizard/issues
Project-URL: Repository, https://github.com/CloudReactor/cloudreactor-aws-setup-wizard
